tuo_ml/__init__.py
tuo_ml/train.py
tuo_ml-6.0.0.27.dist-info/METADATA
tuo_ml-6.0.0.27.dist-info/WHEEL
tuo_ml-6.0.0.27.dist-info/entry_points.txt
tuo_ml-6.0.0.27.dist-info/RECORD
