Metadata-Version: 2.1
Name: tuo-ml
Version: 6.0.0.27
Summary: Machine Learning for TUO
Home-page: https://github.com/APN-Pucky/tyrant_optimize
Author: Alexander Puck Neuwirth
Author-email: alexander@neuwirth-informatik.de
Requires-Python: >=3.8,<4.0
Classifier: Programming Language :: Python :: 3
Classifier: Programming Language :: Python :: 3.8
Classifier: Programming Language :: Python :: 3.9
Classifier: Programming Language :: Python :: 3.10
Classifier: Programming Language :: Python :: 3.11
Requires-Dist: deprecation
Requires-Dist: numpy (>=1.24,<2.0)
Requires-Dist: pandas (>=1.5,<2.0)
Requires-Dist: pyyaml
Requires-Dist: scikit-learn (>=1.1,<2.0)
Requires-Dist: sklearn2pmml (>=0.92,<0.93)
Requires-Dist: smpl_io (>=1.1.0,<2.0.0)
Requires-Dist: tqdm
Requires-Dist: xgboost (>=1.6,<2.0)
Project-URL: Repository, https://github.com/APN-Pucky/tyrant_optimize
